bitrot.py
bitrot_decay-0.0.9.dist-info/METADATA
bitrot_decay-0.0.9.dist-info/WHEEL
bitrot_decay-0.0.9.dist-info/top_level.txt
bitrot_decay-0.0.9.dist-info/RECORD
