Metadata-Version: 2.4
Name: bitrot-decay
Version: 0.0.9
Summary: A lightweight library for simulating digital image decay.
Author-email: Tirthik Durgam <your.email@example.com>
Project-URL: Homepage, https://github.com/tirthikdurgam/bitrot-decay
Classifier: Programming Language :: Python :: 3
Classifier: License :: OSI Approved :: MIT License
Classifier: Operating System :: OS Independent
Requires-Python: >=3.7
Requires-Dist: Pillow
Requires-Dist: numpy
